[
    {
        "ID": 1,
        "Question": "Choose the word whose underlined part is pronounced differently from that of the others:",
        "A": "honest",
        "B": "hour",
        "C": "honor",
        "D": "hotel",
        "Answer": "D",
        "Explain": "Chữ 'h' trong 'hotel' được phát âm, trong khi ở 'honest', 'hour' và 'honor', chữ 'h' là âm câm.",
        "Grammar": "Ngữ Âm - Phát Âm 'h'"
    },
    {
        "ID": 2,
        "Question": "Choose the word whose underlined part is pronounced differently from that of the others:",
        "A": "leave",
        "B": "great",
        "C": "meat",
        "D": "seat",
        "Answer": "B",
        "Explain": "Phần 'ea' trong 'great' được phát âm là /eɪ/, trong khi ở 'leave', 'meat' và 'seat', nó được phát âm là /iː/.",
        "Grammar": "Ngữ Âm - Phát Âm 'ea'"
    },
    {
        "ID": 3,
        "Question": "Choose the word whose primary stress is placed differently from that of the others:",
        "A": "entertain",
        "B": "volunteer",
        "C": "education",
        "D": "understand",
        "Answer": "C",
        "Explain": "Trọng âm trong 'education' rơi vào âm tiết thứ ba ('ca'), trong khi ở các từ khác, trọng âm rơi vào âm tiết cuối cùng.",
        "Grammar": "Ngữ Âm - Trọng Âm"
    },
    {
        "ID": 4,
        "Question": "Choose the word whose primary stress is placed differently from that of the others:",
        "A": "confident",
        "B": "difficult",
        "C": "important",
        "D": "beautiful",
        "Answer": "C",
        "Explain": "Trọng âm trong 'important' rơi vào âm tiết thứ hai, trong khi ở các từ khác, trọng âm rơi vào âm tiết thứ nhất.",
        "Grammar": "Ngữ Âm - Trọng Âm"
    },
    {
        "ID": 5,
        "Question": "If I had known about the accident, I ______ sooner.",
        "A": "would come",
        "B": "would have come",
        "C": "will come",
        "D": "came",
        "Answer": "B",
        "Explain": "Đây là câu điều kiện loại 3 (điều kiện không có thật trong quá khứ): If + S + had + P.P, S + would have + P.P.",
        "Grammar": "Ngữ Pháp - Câu Điều Kiện Loại 3"
    },
    {
        "ID": 6,
        "Question": "He asked me ______ I was doing.",
        "A": "what",
        "B": "which",
        "C": "that",
        "D": "whether",
        "Answer": "A",
        "Explain": "Đây là câu hỏi gián tiếp. Chúng ta dùng 'what' để chỉ một sự vật hoặc hành động.",
        "Grammar": "Ngữ Pháp - Câu Hỏi Gián Tiếp"
    },
    {
        "ID": 7,
        "Question": "Despite ______ hard, he failed the exam.",
        "A": "studying",
        "B": "he studied",
        "C": "to study",
        "D": "he studies",
        "Answer": "A",
        "Explain": "Sau 'despite', chúng ta dùng danh động từ (V-ing) hoặc một cụm danh từ.",
        "Grammar": "Ngữ Pháp - Giới Từ (Despite/In spite of)"
    },
    {
        "ID": 8,
        "Question": "The book ______ on the table belongs to my sister.",
        "A": "laying",
        "B": "lied",
        "C": "lying",
        "D": "laid",
        "Answer": "C",
        "Explain": "Động từ 'lie' (nằm) ở dạng phân từ hiện tại là 'lying'. 'Lay' (đặt) là một ngoại động từ (cần tân ngữ).",
        "Grammar": "Ngữ Pháp - Phân Biệt Lie/Lay"
    },
    {
        "ID": 9,
        "Question": "By the time we arrived, the movie ______.",
        "A": "started",
        "B": "has started",
        "C": "had started",
        "D": "was starting",
        "Answer": "C",
        "Explain": "Câu này diễn tả một hành động đã hoàn thành trước một hành động khác trong quá khứ, vì vậy dùng thì Quá Khứ Hoàn Thành (had started).",
        "Grammar": "Ngữ Pháp - Thì Quá Khứ Hoàn Thành"
    },
    {
        "ID": 10,
        "Question": "She is looking forward to ______ her grandparents.",
        "A": "visit",
        "B": "visiting",
        "C": "be visited",
        "D": "visited",
        "Answer": "B",
        "Explain": "'Look forward to' là một thành ngữ phổ biến theo sau bởi danh động từ (V-ing).",
        "Grammar": "Ngữ Pháp - Cấu Trúc 'Look forward to'"
    },
    {
        "ID": 11,
        "Question": "It's imperative that he ______ the report by tomorrow.",
        "A": "finishes",
        "B": "finished",
        "C": "finish",
        "D": "will finish",
        "Answer": "C",
        "Explain": "Sau 'imperative' (và các tính từ tương tự như 'essential', 'important'), chúng ta dùng thể giả định (dạng nguyên thể của động từ).",
        "Grammar": "Ngữ Pháp - Thể Giả Định (Subjunctive)"
    },
    {
        "ID": 12,
        "Question": "The more you read, ______ you learn.",
        "A": "the more",
        "B": "the most",
        "C": "more",
        "D": "most",
        "Answer": "A",
        "Explain": "Đây là cấu trúc so sánh kép: The + so sánh hơn, the + so sánh hơn.",
        "Grammar": "Ngữ Pháp - So Sánh Kép"
    },
    {
        "ID": 13,
        "Question": "I wish I ______ enough money to buy that car.",
        "A": "have",
        "B": "had",
        "C": "will have",
        "D": "would have",
        "Answer": "B",
        "Explain": "Để diễn tả một mong ước ở hiện tại, chúng ta dùng thì quá khứ đơn sau 'wish'.",
        "Grammar": "Ngữ Pháp - Câu Ước Ở Hiện Tại"
    },
    {
        "ID": 14,
        "Question": "______ he was rich, he wasn't happy.",
        "A": "Despite",
        "B": "Although",
        "C": "Because",
        "D": "Since",
        "Answer": "B",
        "Explain": "'Although' được dùng để giới thiệu một mệnh đề phụ nêu ra một sự thật tương phản với mệnh đề chính.",
        "Grammar": "Ngữ Pháp - Liên Từ Đối Lập (Although/Though/Even though)"
    },
    {
        "ID": 15,
        "Question": "Could you tell me where ______?",
        "A": "does he live",
        "B": "he lives",
        "C": "he does live",
        "D": "lives he",
        "Answer": "B",
        "Explain": "Trong câu hỏi gián tiếp, trật tự từ là chủ ngữ + động từ (không đảo ngữ).",
        "Grammar": "Ngữ Pháp - Câu Hỏi Gián Tiếp"
    },
    {
        "ID": 16,
        "Question": "He advised me ______ in such a bad company.",
        "A": "not to invest",
        "B": "not investing",
        "C": "to not invest",
        "D": "don't invest",
        "Answer": "A",
        "Explain": "'Advise' theo sau bởi 'to + động từ nguyên mẫu' cho lời khuyên khẳng định, và 'not to + động từ nguyên mẫu' cho lời khuyên phủ định.",
        "Grammar": "Ngữ Pháp - Cấu Trúc 'Advise'"
    },
    {
        "ID": 17,
        "Question": "The new manager is very ______ to innovation.",
        "A": "open",
        "B": "opening",
        "C": "openly",
        "D": "opened",
        "Answer": "A",
        "Explain": "'Open to' là một thành ngữ phổ biến có nghĩa là sẵn sàng tiếp nhận điều gì đó mới.",
        "Grammar": "Ngữ Pháp - Thành Ngữ (Open to)"
    },
    {
        "ID": 18,
        "Question": "She can speak English as ______ as a native speaker.",
        "A": "fluent",
        "B": "fluently",
        "C": "fluid",
        "D": "fluidity",
        "Answer": "B",
        "Explain": "Chúng ta cần một trạng từ ('fluently') để bổ nghĩa cho động từ 'speak'.",
        "Grammar": "Ngữ Pháp - Trạng Từ"
    },
    {
        "ID": 19,
        "Question": "By the end of next month, I ______ on this project for three years.",
        "A": "will work",
        "B": "will have worked",
        "C": "have worked",
        "D": "am working",
        "Answer": "B",
        "Explain": "Câu này diễn tả một hành động sẽ hoàn thành trước một thời điểm cụ thể trong tương lai, vì vậy dùng thì Tương Lai Hoàn Thành ('will have worked').",
        "Grammar": "Ngữ Pháp - Thì Tương Lai Hoàn Thành"
    },
    {
        "ID": 20,
        "Question": "If only I ______ how to swim!",
        "A": "knew",
        "B": "know",
        "C": "had known",
        "D": "would know",
        "Answer": "A",
        "Explain": "'If only' theo sau bởi thì quá khứ đơn diễn tả một mong ước về hiện tại.",
        "Grammar": "Ngữ Pháp - Câu Ước Ở Hiện Tại (If only)"
    },
    {
        "ID": 21,
        "Question": "A: 'Could you give me a hand with this box?' B: '______'",
        "A": "Sure, no problem.",
        "B": "No, thanks.",
        "C": "Yes, I can.",
        "D": "All are correct.",
        "Answer": "A",
        "Explain": "Đây là cách chấp nhận lời đề nghị giúp đỡ một cách phổ biến và lịch sự.",
        "Grammar": "Giao Tiếp - Chấp Nhận Lời Giúp Đỡ"
    },
    {
        "ID": 22,
        "Question": "A: 'How do you like your new job?' B: '______'",
        "A": "It's fantastic!",
        "B": "I like it too.",
        "C": "I don't like.",
        "D": "Yes, I do.",
        "Answer": "A",
        "Explain": "Đây là một phản hồi tích cực và phù hợp cho câu hỏi về mức độ hài lòng với công việc.",
        "Grammar": "Giao Tiếp - Hỏi/Đáp Về Sự Hài Lòng"
    },
    {
        "ID": 23,
        "Question": "Find the word CLOSEST in meaning to the underlined word in the following sentence: 'The company decided to _expand_ its business into new markets.'",
        "A": "reduce",
        "B": "enlarge",
        "C": "contract",
        "D": "limit",
        "Answer": "B",
        "Explain": "'Expand' có nghĩa là trở nên hoặc làm cho lớn hơn, rộng hơn. 'Enlarge' là từ gần nghĩa nhất.",
        "Grammar": "Từ Vựng - Đồng Nghĩa"
    },
    {
        "ID": 24,
        "Question": "Find the word OPPOSITE in meaning to the underlined word in the following sentence: 'Her _optimistic_ outlook helped her through difficult times.'",
        "A": "positive",
        "B": "hopeful",
        "C": "pessimistic",
        "D": "cheerful",
        "Answer": "C",
        "Explain": "'Optimistic' có nghĩa là hy vọng và tự tin về tương lai. 'Pessimistic' có nghĩa là có xu hướng nhìn thấy mặt xấu nhất của mọi thứ hoặc tin rằng điều tồi tệ nhất sẽ xảy ra.",
        "Grammar": "Từ Vựng - Trái Nghĩa"
    },
    {
        "ID": 25,
        "Question": "She denied ______ the secret.",
        "A": "telling",
        "B": "to tell",
        "C": "told",
        "D": "tell",
        "Answer": "A",
        "Explain": "Động từ 'deny' thường theo sau bởi một danh động từ (V-ing).",
        "Grammar": "Ngữ Pháp - Động Từ Theo Sau Bởi Gerund"
    },
    {
        "ID": 26,
        "Question": "It was such a boring speech that I ______ asleep.",
        "A": "fall",
        "B": "fell",
        "C": "have fallen",
        "D": "had fallen",
        "Answer": "B",
        "Explain": "Câu này mô tả một hành động trong quá khứ là kết quả của một nguyên nhân trong quá khứ, vì vậy dùng thì quá khứ đơn ('fell').",
        "Grammar": "Ngữ Pháp - Thì Quá Khứ Đơn"
    },
    {
        "ID": 27,
        "Question": "The more quickly you finish, ______ you can leave.",
        "A": "the sooner",
        "B": "the soonest",
        "C": "sooner",
        "D": "soonest",
        "Answer": "A",
        "Explain": "Đây là cấu trúc so sánh kép: The + so sánh hơn, the + so sánh hơn.",
        "Grammar": "Ngữ Pháp - So Sánh Kép"
    },
    {
        "ID": 28,
        "Question": "Had he studied harder, he ______ the exam.",
        "A": "would pass",
        "B": "would have passed",
        "C": "passed",
        "D": "had passed",
        "Answer": "B",
        "Explain": "Đây là câu điều kiện loại 3 đảo ngữ (If he had studied = Had he studied), vì vậy mệnh đề kết quả là 'would have passed'.",
        "Grammar": "Ngữ Pháp - Câu Điều Kiện Loại 3 Đảo Ngữ"
    },
    {
        "ID": 29,
        "Question": "The problem ______ by the committee yesterday.",
        "A": "was discussed",
        "B": "discussed",
        "C": "is discussed",
        "D": "has discussed",
        "Answer": "A",
        "Explain": "Câu này ở thể bị động, diễn tả một hành động trong quá khứ. Do đó, dùng 'was discussed'.",
        "Grammar": "Ngữ Pháp - Thể Bị Động"
    },
    {
        "ID": 30,
        "Question": "I used ______ to school by bike when I was young.",
        "A": "go",
        "B": "going",
        "C": "to go",
        "D": "gone",
        "Answer": "C",
        "Explain": "'Used to + động từ nguyên mẫu' dùng để diễn tả một thói quen hoặc trạng thái trong quá khứ mà hiện tại không còn nữa.",
        "Grammar": "Ngữ Pháp - Cấu Trúc 'Used to'"
    },
    {
        "ID": 31,
        "Question": "He suggested ______ out for dinner.",
        "A": "to go",
        "B": "going",
        "C": "go",
        "D": "went",
        "Answer": "B",
        "Explain": "Động từ 'suggest' theo sau bởi một danh động từ (V-ing).",
        "Grammar": "Ngữ Pháp - Động Từ Theo Sau Bởi Gerund"
    },
    {
        "ID": 32,
        "Question": "The train had already left ______ we arrived at the station.",
        "A": "until",
        "B": "by the time",
        "C": "while",
        "D": "as soon as",
        "Answer": "B",
        "Explain": "'By the time' được dùng để chỉ rằng điều gì đó đã xảy ra trước một thời điểm nhất định trong quá khứ.",
        "Grammar": "Ngữ Pháp - Liên Từ Thời Gian (By the time)"
    },
    {
        "ID": 33,
        "Question": "If you heat water, it ______.",
        "A": "will boil",
        "B": "boils",
        "C": "would boil",
        "D": "boiled",
        "Answer": "B",
        "Explain": "Đây là câu điều kiện loại 0 (diễn tả sự thật hiển nhiên), vì vậy cả hai mệnh đề đều dùng thì hiện tại đơn.",
        "Grammar": "Ngữ Pháp - Câu Điều Kiện Loại 0"
    },
    {
        "ID": 34,
        "Question": "I regret ______ you that your application has been unsuccessful.",
        "A": "inform",
        "B": "informing",
        "C": "to inform",
        "D": "informed",
        "Answer": "C",
        "Explain": "'Regret to inform' có nghĩa là lấy làm tiếc khi phải báo tin xấu. 'Regret + V-ing' có nghĩa là hối tiếc về điều gì đó đã làm trong quá khứ.",
        "Grammar": "Ngữ Pháp - Động Từ Theo Sau Bởi Gerund/To-infinitive (Regret)"
    },
    {
        "ID": 35,
        "Question": "The man ______ car was stolen reported it to the police.",
        "A": "who",
        "B": "whose",
        "C": "whom",
        "D": "which",
        "Answer": "B",
        "Explain": "'Whose' là đại từ sở hữu được dùng để chỉ sự sở hữu.",
        "Grammar": "Ngữ Pháp - Đại Từ Quan Hệ (Whose)"
    },
    {
        "ID": 36,
        "Question": "She couldn't help ______ when she heard the funny story.",
        "A": "laugh",
        "B": "to laugh",
        "C": "laughing",
        "D": "laughed",
        "Answer": "C",
        "Explain": "'Can't help + V-ing' có nghĩa là không thể ngừng làm gì đó.",
        "Grammar": "Ngữ Pháp - Cấu Trúc 'Can't help'"
    },
    {
        "ID": 37,
        "Question": "A: 'Thank you for your help.' B: '______'",
        "A": "You're welcome.",
        "B": "No problem.",
        "C": "It's alright.",
        "D": "All are correct.",
        "Answer": "D",
        "Explain": "Tất cả các lựa chọn đều là những cách lịch sự và phù hợp để đáp lại lời cảm ơn.",
        "Grammar": "Giao Tiếp - Đáp Lại Lời Cảm Ơn"
    },
    {
        "ID": 38,
        "Question": "Choose the word whose underlined part is pronounced differently from that of the others: A. ch_ea_p B. ch_e_mical C. m_e_chanical D. techn_i_que",
        "A": "cheap",
        "B": "chemical",
        "C": "mechanical",
        "D": "technique",
        "Answer": "A",
        "Explain": "Phần 'ea' trong 'cheap' được phát âm là /iː/, trong khi 'che', 'me', 'te' được phát âm là /k/.",
        "Grammar": "Ngữ Âm - Phát Âm 'ea', 'ch', 'e', 'i'"
    },
    {
        "ID": 39,
        "Question": "Choose the word whose primary stress is placed differently from that of the others: A. 'economy B. 'photography C. 'geography D. 'activity",
        "A": "economy",
        "B": "photography",
        "C": "geography",
        "D": "activity",
        "Answer": "D",
        "Explain": "Trọng âm trong 'activity' rơi vào âm tiết thứ hai ('ti'), trong khi ở các từ khác, trọng âm rơi vào âm tiết thứ ba.",
        "Grammar": "Ngữ Âm - Trọng Âm"
    },
    {
        "ID": 40,
        "Question": "The factory is expected ______ in operation by next year.",
        "A": "be",
        "B": "to be",
        "C": "being",
        "D": "to being",
        "Answer": "B",
        "Explain": "'Be expected to + động từ nguyên mẫu' là một cấu trúc bị động phổ biến.",
        "Grammar": "Ngữ Pháp - Cấu Trúc Bị Động 'Be expected to'"
    }
]